bytewax_valkey/__init__.py
bytewax_valkey/py.typed
bytewax_valkey/types.py
bytewax_valkey/inputs/__init__.py
bytewax_valkey/inputs/pubsub_pattern_source.py
bytewax_valkey/inputs/pubsub_source.py
bytewax_valkey/inputs/stream_source.py
bytewax_valkey/outputs/__init__.py
bytewax_valkey/outputs/pubsub_sink.py
bytewax_valkey/outputs/stream_sink.py
bytewax_valkey-0.3.0.dist-info/METADATA
bytewax_valkey-0.3.0.dist-info/WHEEL
bytewax_valkey-0.3.0.dist-info/licenses/LICENSE
bytewax_valkey-0.3.0.dist-info/RECORD
