Metadata-Version: 2.4
Name: bytewax-valkey
Version: 0.3.0
Summary: Valkey connectors for Bytewax
Project-URL: Repository, https://github.com/imnotjames/bytewax-valkey.git
Project-URL: Issues, https://github.com/imnotjames/bytewax-valkey/issues
Author-email: James Ward <james@notjam.es>
License-Expression: MIT
License-File: LICENSE
Keywords: bytewax,valkey
Requires-Python: >=3.12
Requires-Dist: bytewax>=0.21.1
Requires-Dist: valkey>=6.0.2
